k7eel/__init__.py
k7eel/main.py
fucknukerbro-0.1.1.dist-info/METADATA
fucknukerbro-0.1.1.dist-info/WHEEL
fucknukerbro-0.1.1.dist-info/entry_points.txt
fucknukerbro-0.1.1.dist-info/top_level.txt
fucknukerbro-0.1.1.dist-info/RECORD
